MANIFEST.in
README.md
setup.py
psd/__init__.py
psd/convert.py
psd/psd.py
psd.egg-info/PKG-INFO
psd.egg-info/SOURCES.txt
psd.egg-info/dependency_links.txt
psd.egg-info/entry_points.txt
psd.egg-info/not-zip-safe
psd.egg-info/requires.txt
psd.egg-info/top_level.txt