Metadata-Version: 2.1
Name: psd
Version: 1.5
Summary: Python tools for data visualization and spectral analysis.
Home-page: https://gitlab.in2p3.fr/j2b.bayle/psd
Author: Jean-Baptiste Bayle (APC/CNRS/CNES)
Author-email: bayle@apc.in2p3.fr
License: GNU GPLv3
Platform: UNKNOWN
